mirforms/__init__.py
mirforms/apps.py
mirforms/classes.py
mirforms/fields.py
mirforms/templates/mirforms/widgets/htmx_select/htmx_select.html
mirforms/templates/mirforms/widgets/htmx_select/htmx_select_attrs.html
mirforms/templates/mirforms/widgets/htmx_select/htmx_select_option.html
mirforms/templates/mirforms/widgets/htmx_select/htmx_select_wrapper.html
mirforms/tests.py
mirforms/urls.py
mirforms/utils.py
mirforms/views.py
mirforms/widgets.py
django_mirforms-0.1.0.dist-info/LICENSE
django_mirforms-0.1.0.dist-info/WHEEL
django_mirforms-0.1.0.dist-info/METADATA
django_mirforms-0.1.0.dist-info/RECORD
